glemos/__init__.py
glemos/ping.py
glemos-0.0.1.dist-info/LICENSE
glemos-0.0.1.dist-info/METADATA
glemos-0.0.1.dist-info/WHEEL
glemos-0.0.1.dist-info/top_level.txt
glemos-0.0.1.dist-info/RECORD
