Metadata-Version: 2.1
Name: glemos
Version: 0.0.1
Summary: A small example package
Author-email: Guilherme de Lemos <guilherme.eti@gmail.com>
Project-URL: Homepage, https://github.com/guilhermedelemos/glemos-python
Project-URL: Bug Tracker, https://github.com/guilhermedelemos/glemos-python/issues
Classifier: Programming Language :: Python :: 3
Classifier: License :: OSI Approved :: MIT License
Classifier: Operating System :: OS Independent
Requires-Python: >=3.7
License-File: LICENSE
